toolpack/__init__.py
toolpack/parallel/__init__.py
toolpack/parallel/parallel.py
toolpack-0.0.5.dist-info/LICENSE
toolpack-0.0.5.dist-info/METADATA
toolpack-0.0.5.dist-info/WHEEL
toolpack-0.0.5.dist-info/top_level.txt
toolpack-0.0.5.dist-info/RECORD
