Metadata-Version: 2.1
Name: toolpack
Version: 0.0.5
Summary: toolpack for python development tools package
Home-page: https://github.com/MTamon/DevLib.git
Author: Tamon Mikawa
Author-email: mtamon.engineering@gmail.com
License: MIT License
Keywords: devlopment,tools,parallel
Classifier: Development Status :: 4 - Beta
Classifier: License :: OSI Approved :: MIT License
Classifier: Programming Language :: Python
Classifier: Programming Language :: Python :: 3
Classifier: Programming Language :: Python :: 3.9
Classifier: Topic :: Software Development :: Libraries :: Python Modules
License-File: LICENSE
Requires-Dist: joblib (>=1.3.2)
Requires-Dist: tqdm (>=4.64.1)
